boomgate/__init__.py
boomgate/cached_http.py
boomgate/cli.py
boomgate/inspect.py
boomgate/logging.py
boomgate/vulnerabilities.py
boomgate/ecosystems/__init__.py
boomgate/ecosystems/pypi.py
boomgate-0.0.5.dist-info/METADATA
boomgate-0.0.5.dist-info/WHEEL
boomgate-0.0.5.dist-info/entry_points.txt
boomgate-0.0.5.dist-info/licenses/LICENSE
boomgate-0.0.5.dist-info/RECORD
