Metadata-Version: 2.3
Name: boomgate
Version: 0.0.5
Summary: A software supply chain risk management tool
Project-URL: Homepage, https://github.com/KyeRussell/boomgate
Project-URL: Issues, https://github.com/KyeRussell/boomgate/issues
Author-email: Kye Russell <me@kye.id.au>
License:                     GNU AFFERO GENERAL PUBLIC LICENSE
License-File: LICENSE
Keywords: dependency,security,supply chain
Classifier: Development Status :: 1 - Planning
Classifier: Environment :: Console
Classifier: License :: OSI Approved :: GNU Affero General Public License v3 or later (AGPLv3+)
Classifier: Natural Language :: English
Classifier: Topic :: Security
Classifier: Topic :: Software Development
Classifier: Topic :: System :: Archiving :: Packaging
Classifier: Topic :: Utilities
Requires-Python: >=3.11
Requires-Dist: httpx
Requires-Dist: rich
Requires-Dist: typer
Provides-Extra: dev
Requires-Dist: build; extra == 'dev'
Requires-Dist: hatch; extra == 'dev'
Requires-Dist: mypy; extra == 'dev'
Requires-Dist: pre-commit; extra == 'dev'
Requires-Dist: ruff; extra == 'dev'
